{
  "applications": "*",
  "changelogDate": "20221120112058",
  "dto": "mapstruct",
  "embedded": false,
  "entityTableName": "district",
  "fields": [
    {
      "fieldName": "name",
      "fieldType": "String",
      "fieldValidateRules": ["required", "maxlength", "unique"],
      "fieldValidateRulesMaxlength": "128"
    },
    {
      "fieldName": "info",
      "fieldType": "String",
      "fieldValidateRules": ["maxlength"],
      "fieldValidateRulesMaxlength": "1024"
    }
  ],
  "fluentMethods": true,
  "javadoc": "Район.",
  "jpaMetamodelFiltering": false,
  "name": "District",
  "pagination": "pagination",
  "readOnly": false,
  "relationships": [
    {
      "otherEntityName": "city",
      "relationshipName": "city",
      "relationshipType": "many-to-one"
    }
  ],
  "service": "serviceImpl"
}
